mypackage/__init__.py
mypackage/mymodule.py
tests/__init__.py
tests/test_mymodule.py
lu_package-0.1.0.dist-info/LICENSE
lu_package-0.1.0.dist-info/METADATA
lu_package-0.1.0.dist-info/WHEEL
lu_package-0.1.0.dist-info/top_level.txt
lu_package-0.1.0.dist-info/RECORD
