Metadata-Version: 2.1
Name: lu-package
Version: 0.1.0
Summary: Practice Package
Home-page: https://github.com/luffyZZang/python-study
Author: lulu
Author-email: guswn247@naver.com
Classifier: Programming Language :: Python :: 3
Classifier: License :: OSI Approved :: MIT License
Classifier: Operating System :: OS Independent
Requires-Python: >=3.12
License-File: LICENSE
